{
  "todos": [
    {
      "id": 1734127288414,
      "title": "1",
      "completed": false
    },
    {
      "id": 1734127291939,
      "title": "a",
      "completed": false
    },
    {
      "id": 1734127293149,
      "title": "2",
      "completed": false
    },
    {
      "id": 1734127294346,
      "title": "b",
      "completed": false
    },
    {
      "id": 1734127296147,
      "title": "3",
      "completed": false
    },
    {
      "id": 1734127297339,
      "title": "c",
      "completed": false
    },
    {
      "id": 1734127342213,
      "title": "ab",
      "completed": false
    },
    {
      "id": 1734127344339,
      "title": "abc",
      "completed": false
    },
    {
      "id": 1734127347061,
      "title": "ab1",
      "completed": false
    }
  ]
}